expense_tracker/__init__.py
expense_tracker/app.py
expense_tracker/expensetracker.py
expense_tracker/expensetrackerclass.py
expense_tracker/remotefunc.py
expense_tracker-2.0.0.dist-info/LICENSE
expense_tracker-2.0.0.dist-info/METADATA
expense_tracker-2.0.0.dist-info/WHEEL
expense_tracker-2.0.0.dist-info/entry_points.txt
expense_tracker-2.0.0.dist-info/top_level.txt
expense_tracker-2.0.0.dist-info/RECORD
