Metadata-Version: 2.1
Name: expense-tracker
Version: 2.0.0
Summary: Expense Tracker is a very good tool to keep track of your expenseditures and the total money you saved.🤑🤑
Home-page: https://github.com/CapedDemon/EXPENSE-TRACKER
Author: Shreejan Dolai
Author-email: dolaishreejan@gmail.com
Project-URL: Bug Tracker, https://github.com/CapedDemon/EXPENSE-TRACKER/issues
Keywords: expense,tracker,money,py,expense tracker,expense-tracker,money tracker,money-tracker
Classifier: Programming Language :: Python :: 3
Classifier: License :: OSI Approved :: MIT License
Classifier: Operating System :: OS Independent
Requires-Python: >=3.9
License-File: LICENSE
Requires-Dist: matplotlib
Requires-Dist: requests
Requires-Dist: flask
Requires-Dist: bcrypt
